damv1evernoteprojectk8salert/__init__.py
damv1evernoteprojectk8salert/myevernote_projectk8salert.py
damv1evernoteprojectk8salert/production_myevernote_projectk8salert.py
damv1evernoteprojectk8salert/sandbox_myevernote_projectk8salert.py
damv1evernoteprojectk8salert-0.3.10.dist-info/METADATA
damv1evernoteprojectk8salert-0.3.10.dist-info/WHEEL
damv1evernoteprojectk8salert-0.3.10.dist-info/top_level.txt
damv1evernoteprojectk8salert-0.3.10.dist-info/RECORD
