Metadata-Version: 2.1
Name: damv1evernoteprojectk8salert
Version: 0.3.10
Summary: evernote for project kubernetes alert
Home-page: UNKNOWN
Author: dhonyabumuhammad (Bekasi)
Author-email: <dhony.priniardi.m@gmail.com>
License: UNKNOWN
Keywords: evernotek8salert
Platform: UNKNOWN
Classifier: Development Status :: 1 - Planning
Classifier: Intended Audience :: Developers
Classifier: Programming Language :: Python :: 3
Classifier: Operating System :: Unix
Classifier: Operating System :: MacOS :: MacOS X
Classifier: Operating System :: Microsoft :: Windows
Requires-Dist: damv1env
Requires-Dist: damv1time7
Requires-Dist: evernote3
